nonebot_plugin_gsabyss/__init__.py
nonebot_plugin_gsabyss/config.py
nonebot_plugin_gsabyss/data_source.py
nonebot_plugin_gsabyss/draw_quickview.py
nonebot_plugin_gsabyss/draw_statistic.py
nonebot_plugin_gsabyss/draw_utils.py
nonebot_plugin_gsabyss/models/akasha.py
nonebot_plugin_gsabyss/models/hhw.py
nonebot_plugin_gsabyss-0.1.5.dist-info/LICENSE
nonebot_plugin_gsabyss-0.1.5.dist-info/METADATA
nonebot_plugin_gsabyss-0.1.5.dist-info/WHEEL
nonebot_plugin_gsabyss-0.1.5.dist-info/RECORD
