Metadata-Version: 2.1
Name: nonebot-plugin-gsabyss
Version: 0.1.5
Summary: Genshin spiral abyss plugin for NoneBot2
Home-page: https://github.com/monsterxcn/nonebot-plugin-gsabyss
License: MIT
Keywords: nonebot,nonebot2,genshin,abyss
Author: monsterxcn
Author-email: monsterxcn@gmail.com
Requires-Python: >=3.8.1,<4.0
Classifier: License :: OSI Approved :: MIT License
Classifier: Programming Language :: Python :: 3
Classifier: Programming Language :: Python :: 3.9
Classifier: Programming Language :: Python :: 3.10
Classifier: Programming Language :: Python :: 3.11
Requires-Dist: Pillow (>=9.1.0)
Requires-Dist: httpx (>=0.20.0,<1.0.0)
Requires-Dist: nonebot-adapter-onebot (>=2.0.0b1)
Requires-Dist: nonebot-plugin-apscheduler (>=0.2.0)
Requires-Dist: nonebot2 (>=2.0.0b3)
Project-URL: Documentation, https://github.com/monsterxcn/nonebot-plugin-gsabyss#readme
